a2y_handy.cp312-win_amd64.pyd
a2y_handy-2.0.3.dist-info/LICENSE
a2y_handy-2.0.3.dist-info/METADATA
a2y_handy-2.0.3.dist-info/WHEEL
a2y_handy-2.0.3.dist-info/top_level.txt
a2y_handy-2.0.3.dist-info/RECORD
