Metadata-Version: 2.2
Name: a2y_handy
Version: 2.0.3
Summary: A module that contains kinds of little functions and classes that are not easy to classify.
Home-page: http://www.kersci.com/a2y/handy.html
Author: Yu Han
Author-email: hanjunyu@163.com
License: Private
Platform: Windows
Platform: Linux
Classifier: Development Status :: 4 - Beta
Classifier: Intended Audience :: Developers
Classifier: License :: Free For Educational Use
Classifier: Programming Language :: Python :: 3.6
Classifier: Operating System :: Microsoft :: Windows :: Windows 10
Classifier: Operating System :: POSIX :: Linux
License-File: LICENSE
Requires-Dist: openpyxl>=3.0.0
Requires-Dist: watchdog>=2.1.0
Requires-Dist: xlrd==1.2.0
Dynamic: author
Dynamic: author-email
Dynamic: classifier
Dynamic: description
Dynamic: description-content-type
Dynamic: home-page
Dynamic: license
Dynamic: platform
Dynamic: requires-dist
Dynamic: summary
